{"id":"i6mjzatwd5mneu50wqunfzx","title":"Contacts by Vote Propensity","desc":"","updated":1760642316066,"created":1760642316066,"isDir":false,"custom":{"isDir":false},"fname":"contacts-by-vote-propensity","type":"note","vault":{"fsPath":".","selfContained":true,"name":"Dendron"},"contentHash":"18273bd54dea8121d62fd43fbd719324","links":[],"anchors":{"c3-voter-scores":{"type":"header","text":"c3 voter scores","value":"c3-voter-scores","line":8,"column":0,"depth":4},"vote-propensity":{"type":"header","text":"vote propensity","value":"vote-propensity","line":36,"column":0,"depth":4}},"children":[],"parent":"root","data":{}}
